{"text": " I'm through with love, I'll never fall again Said I do to love, don't ever call again For I must have you or no one That's why I'm through With love I've locked my heart I keep my feelings there I have stopped my heart Like an icy frigid air For I need to care for no one That's why I'm through With love Why did you leave me With love? To think that you cared You didn't need me For you and your share Of slaves around you To hound you and swear The deep delusion Emotion Dear good By the spring And all it meant to me It could never breathe The things that used to be The things that used to be For I must have you or no one That's why I'm through With love That's why I'm through That's why I am through with love I am through with love", "segments": [{"id": 0, "seek": 0, "start": 11.580000000000002, "end": 18.76, "text": " I'm through with love, I'll never fall again", "tokens": [50365, 286, 478, 807, 365, 959, 11, 286, 603, 1128, 2100, 797, 51315], "temperature": 0.0, "avg_logprob": -0.5232794443766277, "compression_ratio": 0.88, "no_speech_prob": 0.09603206813335419, "words": [{"word": " I'm", "start": 11.580000000000002, "end": 12.7, "probability": 0.8914458751678467}, {"word": " through", "start": 12.7, "end": 12.98, "probability": 0.903246283531189}, {"word": " with", "start": 12.98, "end": 13.36, "probability": 0.9857271313667297}, {"word": " love,", "start": 13.36, "end": 14.32, "probability": 0.9836122393608093}, {"word": " I'll", "start": 14.48, "end": 16.34, "probability": 0.966278463602066}, {"word": " never", "start": 16.34, "end": 16.9, "probability": 0.9984768033027649}, {"word": " fall", "start": 16.9, "end": 18.26, "probability": 0.9727315306663513}, {"word": " again", "start": 18.26, "end": 18.76, "probability": 0.9984875917434692}]}, {"id": 1, "seek": 1876, "start": 21.26, "end": 29.42, "text": " Said I do to love, don't ever call again", "tokens": [50365, 26490, 286, 360, 281, 959, 11, 500, 380, 1562, 818, 797, 50915], "temperature": 0.0, "avg_logprob": -0.2738111380374793, "compression_ratio": 1.0689655172413792, "no_speech_prob": 0.01104132179170847, "words": [{"word": " Said", "start": 21.26, "end": 22.32, "probability": 0.3174530267715454}, {"word": " I", "start": 22.32, "end": 22.54, "probability": 0.6942001581192017}, {"word": " do", "start": 22.54, "end": 22.84, "probability": 0.9139304757118225}, {"word": " to", "start": 22.84, "end": 23.8, "probability": 0.11960602551698685}, {"word": " love,", "start": 23.8, "end": 24.6, "probability": 0.9901216626167297}, {"word": " don't", "start": 24.72, "end": 28.16, "probability": 0.9278738796710968}, {"word": " ever", "start": 28.16, "end": 28.36, "probability": 0.9975460171699524}, {"word": " call", "start": 28.36, "end": 28.92, "probability": 0.9982901215553284}, {"word": " again", "start": 28.92, "end": 29.42, "probability": 0.997832715511322}]}, {"id": 2, "seek": 1876, "start": 32.519999999999996, "end": 38.42, "text": " For I must have you or no one", "tokens": [50915, 1171, 286, 1633, 362, 291, 420, 572, 472, 51515], "temperature": 0.0, "avg_logprob": -0.2738111380374793, "compression_ratio": 1.0689655172413792, "no_speech_prob": 0.01104132179170847, "words": [{"word": " For", "start": 32.519999999999996, "end": 33.58, "probability": 0.6283596158027649}, {"word": " I", "start": 33.58, "end": 34.64, "probability": 0.9954738020896912}, {"word": " must", "start": 34.64, "end": 35.0, "probability": 0.9972867965698242}, {"word": " have", "start": 35.0, "end": 35.3, "probability": 0.9961827397346497}, {"word": " you", "start": 35.3, "end": 35.78, "probability": 0.9705783724784851}, {"word": " or", "start": 35.78, "end": 37.06, "probability": 0.2650606334209442}, {"word": " no", "start": 37.06, "end": 37.6, "probability": 0.9933204650878906}, {"word": " one", "start": 37.6, "end": 38.42, "probability": 0.9860397577285767}]}, {"id": 3, "seek": 1876, "start": 44.46000000000001, "end": 46.52, "text": " That's why I'm through", "tokens": [51515, 663, 311, 983, 286, 478, 807, 51815], "temperature": 0.0, "avg_logprob": -0.2738111380374793, "compression_ratio": 1.0689655172413792, "no_speech_prob": 0.01104132179170847, "words": [{"word": " That's", "start": 44.46000000000001, "end": 45.52, "probability": 0.8827053308486938}, {"word": " why", "start": 45.52, "end": 45.72, "probability": 0.979910135269165}, {"word": " I'm", "start": 45.72, "end": 46.24, "probability": 0.9940140545368195}, {"word": " through", "start": 46.24, "end": 46.52, "probability": 0.9922290444374084}]}, {"id": 4, "seek": 4652, "start": 49.099999999999994, "end": 51.02, "text": " With love", "tokens": [50365, 2022, 959, 50865], "temperature": 0.0, "avg_logprob": -0.15536884700550752, "compression_ratio": 1.186046511627907, "no_speech_prob": 0.002559822052717209, "words": [{"word": " With", "start": 49.099999999999994, "end": 50.22, "probability": 0.14405426383018494}, {"word": " love", "start": 50.22, "end": 51.02, "probability": 0.8602381348609924}]}, {"id": 5, "seek": 4652, "start": 56.239999999999995, "end": 58.44, "text": " I've locked my heart", "tokens": [50865, 286, 600, 9376, 452, 1917, 51115], "temperature": 0.0, "avg_logprob": -0.15536884700550752, "compression_ratio": 1.186046511627907, "no_speech_prob": 0.002559822052717209, "words": [{"word": " I've", "start": 56.239999999999995, "end": 57.36, "probability": 0.736961156129837}, {"word": " locked", "start": 57.36, "end": 57.62, "probability": 0.985800564289093}, {"word": " my", "start": 57.62, "end": 57.88, "probability": 0.9980104565620422}, {"word": " heart", "start": 57.88, "end": 58.44, "probability": 0.998676598072052}]}, {"id": 6, "seek": 4652, "start": 60.17999999999999, "end": 63.7, "text": " I keep my feelings there", "tokens": [51115, 286, 1066, 452, 6640, 456, 51315], "temperature": 0.0, "avg_logprob": -0.15536884700550752, "compression_ratio": 1.186046511627907, "no_speech_prob": 0.002559822052717209, "words": [{"word": " I", "start": 60.17999999999999, "end": 61.3, "probability": 0.8614153861999512}, {"word": " keep", "start": 61.3, "end": 62.32, "probability": 0.9805942177772522}, {"word": " my", "start": 62.32, "end": 62.7, "probability": 0.9986951947212219}, {"word": " feelings", "start": 62.7, "end": 63.26, "probability": 0.994030773639679}, {"word": " there", "start": 63.26, "end": 63.7, "probability": 0.8924867510795593}]}, {"id": 7, "seek": 4652, "start": 65.1, "end": 69.84, "text": " I have stopped my heart", "tokens": [51315, 286, 362, 5936, 452, 1917, 51715], "temperature": 0.0, "avg_logprob": -0.15536884700550752, "compression_ratio": 1.186046511627907, "no_speech_prob": 0.002559822052717209, "words": [{"word": " I", "start": 65.1, "end": 66.22, "probability": 0.9758944511413574}, {"word": " have", "start": 66.22, "end": 66.6, "probability": 0.9803676605224609}, {"word": " stopped", "start": 66.6, "end": 67.12, "probability": 0.9402673244476318}, {"word": " my", "start": 67.12, "end": 69.0, "probability": 0.7309749126434326}, {"word": " heart", "start": 69.0, "end": 69.84, "probability": 0.9983267188072205}]}, {"id": 8, "seek": 4652, "start": 73.22, "end": 76.02, "text": " Like an icy frigid air", "tokens": [51715, 1743, 364, 42015, 34697, 327, 1988, 51865], "temperature": 0.0, "avg_logprob": -0.15536884700550752, "compression_ratio": 1.186046511627907, "no_speech_prob": 0.002559822052717209, "words": [{"word": " Like", "start": 73.22, "end": 74.34, "probability": 0.9464617371559143}, {"word": " an", "start": 74.34, "end": 74.64, "probability": 0.9941666126251221}, {"word": " icy", "start": 74.64, "end": 74.98, "probability": 0.9843855500221252}, {"word": " frigid", "start": 74.98, "end": 75.6, "probability": 0.8812417984008789}, {"word": " air", "start": 75.6, "end": 76.02, "probability": 0.8659387230873108}]}, {"id": 9, "seek": 7652, "start": 79.08000000000001, "end": 84.2, "text": " For I need to care for no one", "tokens": [50365, 1171, 286, 643, 281, 1127, 337, 572, 472, 50865], "temperature": 0.0, "avg_logprob": -0.21026714869907925, "compression_ratio": 1.1325301204819278, "no_speech_prob": 0.004029550589621067, "words": [{"word": " For", "start": 79.08000000000001, "end": 80.12, "probability": 0.7302838563919067}, {"word": " I", "start": 80.12, "end": 80.42, "probability": 0.9940973520278931}, {"word": " need", "start": 80.42, "end": 80.82, "probability": 0.9922870397567749}, {"word": " to", "start": 80.82, "end": 81.12, "probability": 0.9905598759651184}, {"word": " care", "start": 81.12, "end": 81.46, "probability": 0.9880461692810059}, {"word": " for", "start": 81.46, "end": 82.4, "probability": 0.9658607840538025}, {"word": " no", "start": 82.4, "end": 83.48, "probability": 0.9676432609558105}, {"word": " one", "start": 83.48, "end": 84.2, "probability": 0.9965147972106934}]}, {"id": 10, "seek": 7652, "start": 90.82, "end": 92.68, "text": " That's why I'm through", "tokens": [50865, 663, 311, 983, 286, 478, 807, 51215], "temperature": 0.0, "avg_logprob": -0.21026714869907925, "compression_ratio": 1.1325301204819278, "no_speech_prob": 0.004029550589621067, "words": [{"word": " That's", "start": 90.82, "end": 91.86, "probability": 0.8000357747077942}, {"word": " why", "start": 91.86, "end": 92.04, "probability": 0.9909359812736511}, {"word": " I'm", "start": 92.04, "end": 92.38, "probability": 0.9966886639595032}, {"word": " through", "start": 92.38, "end": 92.68, "probability": 0.9344851970672607}]}, {"id": 11, "seek": 7652, "start": 93.52, "end": 95.34, "text": " With love", "tokens": [51215, 2022, 959, 51415], "temperature": 0.0, "avg_logprob": -0.21026714869907925, "compression_ratio": 1.1325301204819278, "no_speech_prob": 0.004029550589621067, "words": [{"word": " With", "start": 93.52, "end": 94.76, "probability": 0.005895750597119331}, {"word": " love", "start": 94.76, "end": 95.34, "probability": 0.9821390509605408}]}, {"id": 12, "seek": 7652, "start": 101.44, "end": 104.38, "text": " Why did you leave me", "tokens": [51415, 1545, 630, 291, 1856, 385, 51765], "temperature": 0.0, "avg_logprob": -0.21026714869907925, "compression_ratio": 1.1325301204819278, "no_speech_prob": 0.004029550589621067, "words": [{"word": " Why", "start": 101.44, "end": 102.48, "probability": 0.9034931659698486}, {"word": " did", "start": 102.48, "end": 103.08, "probability": 0.9913440942764282}, {"word": " you", "start": 103.08, "end": 103.48, "probability": 0.9946478009223938}, {"word": " leave", "start": 103.48, "end": 103.86, "probability": 0.9595241546630859}, {"word": " me", "start": 103.86, "end": 104.38, "probability": 0.9991951584815979}]}, {"id": 13, "seek": 7652, "start": 104.38, "end": 106.5, "text": " With love?", "tokens": [51765, 2022, 959, 30, 51815], "temperature": 0.0, "avg_logprob": -0.21026714869907925, "compression_ratio": 1.1325301204819278, "no_speech_prob": 0.004029550589621067, "words": [{"word": " With", "start": 104.38, "end": 106.28, "probability": 0.0003843330196104944}, {"word": " love?", "start": 106.28, "end": 106.5, "probability": 0.4501313269138336}]}, {"id": 14, "seek": 10652, "start": 106.52, "end": 110.9, "text": " To think that you cared", "tokens": [50365, 1407, 519, 300, 291, 19779, 50765], "temperature": 0.0, "avg_logprob": -0.20233159451871305, "compression_ratio": 1.211111111111111, "no_speech_prob": 0.005573547910898924, "words": [{"word": " To", "start": 106.52, "end": 107.82, "probability": 0.4064651429653168}, {"word": " think", "start": 107.82, "end": 109.0, "probability": 0.9674379229545593}, {"word": " that", "start": 109.0, "end": 110.02, "probability": 0.8893266916275024}, {"word": " you", "start": 110.02, "end": 110.36, "probability": 0.9947500824928284}, {"word": " cared", "start": 110.36, "end": 110.9, "probability": 0.9927095174789429}]}, {"id": 15, "seek": 10652, "start": 113.06, "end": 115.98, "text": " You didn't need me", "tokens": [50765, 509, 994, 380, 643, 385, 50965], "temperature": 0.0, "avg_logprob": -0.20233159451871305, "compression_ratio": 1.211111111111111, "no_speech_prob": 0.005573547910898924, "words": [{"word": " You", "start": 113.06, "end": 114.26, "probability": 0.7625097632408142}, {"word": " didn't", "start": 114.26, "end": 115.2, "probability": 0.9945429861545563}, {"word": " need", "start": 115.2, "end": 115.56, "probability": 0.998264729976654}, {"word": " me", "start": 115.56, "end": 115.98, "probability": 0.9976801872253418}]}, {"id": 16, "seek": 10652, "start": 118.52, "end": 121.98, "text": " For you and your share", "tokens": [50965, 1171, 291, 293, 428, 2073, 51365], "temperature": 0.0, "avg_logprob": -0.20233159451871305, "compression_ratio": 1.211111111111111, "no_speech_prob": 0.005573547910898924, "words": [{"word": " For", "start": 118.2, "end": 118.8, "probability": 0.7579887509346008}, {"word": " you", "start": 118.8, "end": 119.12, "probability": 0.9703692197799683}, {"word": " and", "start": 119.12, "end": 120.94, "probability": 0.5943711400032043}, {"word": " your", "start": 120.94, "end": 121.54, "probability": 0.9792979955673218}, {"word": " share", "start": 121.54, "end": 121.98, "probability": 0.8229243755340576}]}, {"id": 17, "seek": 10652, "start": 126.52, "end": 129.06, "text": " Of slaves around you", "tokens": [51365, 2720, 18394, 926, 291, 51615], "temperature": 0.0, "avg_logprob": -0.20233159451871305, "compression_ratio": 1.211111111111111, "no_speech_prob": 0.005573547910898924, "words": [{"word": " Of", "start": 126.2, "end": 126.8, "probability": 0.5161836743354797}, {"word": " slaves", "start": 126.8, "end": 127.3, "probability": 0.8184857368469238}, {"word": " around", "start": 127.3, "end": 128.2, "probability": 0.999187171459198}, {"word": " you", "start": 128.2, "end": 129.06, "probability": 0.9994955062866211}]}, {"id": 18, "seek": 10652, "start": 131.51999999999998, "end": 133.96, "text": " To hound you and swear", "tokens": [51615, 1407, 276, 554, 291, 293, 11902, 51765], "temperature": 0.0, "avg_logprob": -0.20233159451871305, "compression_ratio": 1.211111111111111, "no_speech_prob": 0.005573547910898924, "words": [{"word": " To", "start": 131.51999999999998, "end": 132.16, "probability": 0.9931083917617798}, {"word": " hound", "start": 132.16, "end": 132.72, "probability": 0.8813530504703522}, {"word": " you", "start": 132.72, "end": 133.12, "probability": 0.9994410872459412}, {"word": " and", "start": 133.12, "end": 133.5, "probability": 0.9965831637382507}, {"word": " swear", "start": 133.5, "end": 133.96, "probability": 0.9982965588569641}]}, {"id": 19, "seek": 13396, "start": 136.14, "end": 140.06, "text": " The deep delusion", "tokens": [50365, 440, 2452, 1103, 5704, 50765], "temperature": 0.0, "avg_logprob": -0.3457531520298549, "compression_ratio": 1.0919540229885059, "no_speech_prob": 0.004213350359350443, "words": [{"word": " The", "start": 136.14, "end": 137.54, "probability": 0.03292899206280708}, {"word": " deep", "start": 137.54, "end": 138.94, "probability": 0.9220696687698364}, {"word": " delusion", "start": 138.94, "end": 140.06, "probability": 0.7099649310112}]}, {"id": 20, "seek": 13396, "start": 141.96, "end": 142.74, "text": " Emotion", "tokens": [50765, 3968, 19228, 50865], "temperature": 0.0, "avg_logprob": -0.3457531520298549, "compression_ratio": 1.0919540229885059, "no_speech_prob": 0.004213350359350443, "words": [{"word": " Emotion", "start": 141.96, "end": 142.74, "probability": 0.5206187032163143}]}, {"id": 21, "seek": 13396, "start": 143.96, "end": 147.1, "text": " Dear good", "tokens": [50865, 14383, 665, 51165], "temperature": 0.0, "avg_logprob": -0.3457531520298549, "compression_ratio": 1.0919540229885059, "no_speech_prob": 0.004213350359350443, "words": [{"word": " Dear", "start": 143.96, "end": 145.3, "probability": 0.101822629570961}, {"word": " good", "start": 145.3, "end": 147.1, "probability": 0.6610664129257202}]}, {"id": 22, "seek": 13396, "start": 149.96, "end": 151.56, "text": " By the spring", "tokens": [51165, 3146, 264, 5587, 51415], "temperature": 0.0, "avg_logprob": -0.3457531520298549, "compression_ratio": 1.0919540229885059, "no_speech_prob": 0.004213350359350443, "words": [{"word": " By", "start": 149.96, "end": 150.66, "probability": 0.6914635300636292}, {"word": " the", "start": 150.66, "end": 151.18, "probability": 0.980391263961792}, {"word": " spring", "start": 151.18, "end": 151.56, "probability": 0.9665707945823669}]}, {"id": 23, "seek": 13396, "start": 154.51999999999998, "end": 157.18, "text": " And all it meant to me", "tokens": [51415, 400, 439, 309, 4140, 281, 385, 51615], "temperature": 0.0, "avg_logprob": -0.3457531520298549, "compression_ratio": 1.0919540229885059, "no_speech_prob": 0.004213350359350443, "words": [{"word": " And", "start": 154.51999999999998, "end": 155.92, "probability": 0.9205365180969238}, {"word": " all", "start": 155.92, "end": 156.2, "probability": 0.9963812232017517}, {"word": " it", "start": 156.2, "end": 156.4, "probability": 0.9867201447486877}, {"word": " meant", "start": 156.4, "end": 156.64, "probability": 0.9932920932769775}, {"word": " to", "start": 156.64, "end": 156.86, "probability": 0.9974061846733093}, {"word": " me", "start": 156.86, "end": 157.18, "probability": 0.9974687099456787}]}, {"id": 24, "seek": 13396, "start": 158.96, "end": 161.96, "text": " It could never breathe", "tokens": [51615, 467, 727, 1128, 10192, 51765], "temperature": 0.0, "avg_logprob": -0.3457531520298549, "compression_ratio": 1.0919540229885059, "no_speech_prob": 0.004213350359350443, "words": [{"word": " It", "start": 158.48000000000002, "end": 159.18, "probability": 0.5267515778541565}, {"word": " could", "start": 159.18, "end": 159.48, "probability": 0.8887244462966919}, {"word": " never", "start": 159.48, "end": 160.4, "probability": 0.9624512791633606}, {"word": " breathe", "start": 160.4, "end": 161.96, "probability": 0.6502964496612549}]}, {"id": 25, "seek": 16196, "start": 165.44000000000003, "end": 168.66, "text": " The things that used to be", "tokens": [50365, 440, 721, 300, 1143, 281, 312, 50565], "temperature": 0.8, "avg_logprob": -0.29255566230187047, "compression_ratio": 1.6555555555555554, "no_speech_prob": 0.00646232208237052, "words": [{"word": " The", "start": 165.44000000000003, "end": 166.48000000000002, "probability": 0.4529716968536377}, {"word": " things", "start": 166.48000000000002, "end": 167.52, "probability": 0.9745182394981384}, {"word": " that", "start": 167.52, "end": 167.78, "probability": 0.9941381216049194}, {"word": " used", "start": 167.78, "end": 168.08, "probability": 0.9912459254264832}, {"word": " to", "start": 168.08, "end": 168.36, "probability": 0.9980675578117371}, {"word": " be", "start": 168.36, "end": 168.66, "probability": 0.9969108700752258}]}, {"id": 26, "seek": 16196, "start": 168.66, "end": 173.7, "text": " The things that used to be", "tokens": [50565, 440, 721, 300, 1143, 281, 312, 50665], "temperature": 0.8, "avg_logprob": -0.29255566230187047, "compression_ratio": 1.6555555555555554, "no_speech_prob": 0.00646232208237052, "words": [{"word": " The", "start": 168.66, "end": 170.02, "probability": 0.0028138780035078526}, {"word": " things", "start": 170.02, "end": 173.7, "probability": 0.931659460067749}, {"word": " that", "start": 173.7, "end": 173.7, "probability": 0.9846736192703247}, {"word": " used", "start": 173.7, "end": 173.7, "probability": 0.9874897599220276}, {"word": " to", "start": 173.7, "end": 173.7, "probability": 0.9945291876792908}, {"word": " be", "start": 173.7, "end": 173.7, "probability": 0.99801105260849}]}, {"id": 27, "seek": 16196, "start": 173.7, "end": 178.1, "text": " For I must have you or no one", "tokens": [50665, 1171, 286, 1633, 362, 291, 420, 572, 472, 50965], "temperature": 0.8, "avg_logprob": -0.29255566230187047, "compression_ratio": 1.6555555555555554, "no_speech_prob": 0.00646232208237052, "words": [{"word": " For", "start": 173.7, "end": 173.7, "probability": 0.8698161840438843}, {"word": " I", "start": 173.7, "end": 174.16, "probability": 0.9710653424263}, {"word": " must", "start": 174.16, "end": 174.48, "probability": 0.9970021843910217}, {"word": " have", "start": 174.48, "end": 174.8, "probability": 0.9963588118553162}, {"word": " you", "start": 174.8, "end": 175.22, "probability": 0.9785414338111877}, {"word": " or", "start": 175.22, "end": 176.3, "probability": 0.20138756930828094}, {"word": " no", "start": 176.3, "end": 177.2, "probability": 0.9640812873840332}, {"word": " one", "start": 177.2, "end": 178.1, "probability": 0.991987943649292}]}, {"id": 28, "seek": 16196, "start": 184.20000000000002, "end": 186.5, "text": " That's why I'm through", "tokens": [50965, 663, 311, 983, 286, 478, 807, 51265], "temperature": 0.8, "avg_logprob": -0.29255566230187047, "compression_ratio": 1.6555555555555554, "no_speech_prob": 0.00646232208237052, "words": [{"word": " That's", "start": 184.20000000000002, "end": 185.24, "probability": 0.8892913460731506}, {"word": " why", "start": 185.24, "end": 185.48, "probability": 0.9909494519233704}, {"word": " I'm", "start": 185.48, "end": 186.12, "probability": 0.9828996062278748}, {"word": " through", "start": 186.12, "end": 186.5, "probability": 0.9708705544471741}]}, {"id": 29, "seek": 16196, "start": 188.26000000000002, "end": 189.88, "text": " With love", "tokens": [51265, 2022, 959, 51565], "temperature": 0.8, "avg_logprob": -0.29255566230187047, "compression_ratio": 1.6555555555555554, "no_speech_prob": 0.00646232208237052, "words": [{"word": " With", "start": 188.26000000000002, "end": 189.3, "probability": 0.5878048539161682}, {"word": " love", "start": 189.3, "end": 189.88, "probability": 0.980767011642456}]}, {"id": 30, "seek": 16196, "start": 189.88, "end": 189.96, "text": " That's why I'm through", "tokens": [51565, 663, 311, 983, 286, 478, 807, 51665], "temperature": 0.8, "avg_logprob": -0.29255566230187047, "compression_ratio": 1.6555555555555554, "no_speech_prob": 0.00646232208237052, "words": [{"word": " That's", "start": 189.88, "end": 189.96, "probability": 0.5462289415299892}, {"word": " why", "start": 189.96, "end": 189.96, "probability": 0.9947634935379028}, {"word": " I'm", "start": 189.96, "end": 189.96, "probability": 0.997723251581192}, {"word": " through", "start": 189.96, "end": 189.96, "probability": 0.9976909160614014}]}, {"id": 31, "seek": 16196, "start": 189.96, "end": 189.96, "text": "", "tokens": [], "temperature": 0.8, "avg_logprob": -0.29255566230187047, "compression_ratio": 1.6555555555555554, "no_speech_prob": 0.00646232208237052, "words": []}, {"id": 32, "seek": 18996, "start": 196.01999999999998, "end": 204.18, "text": " That's why I am through with love", "tokens": [50365, 663, 311, 983, 286, 669, 807, 365, 959, 51131], "temperature": 0.0, "avg_logprob": -0.3798661231994629, "compression_ratio": 0.8048780487804879, "no_speech_prob": 0.12295280396938324, "words": [{"word": " That's", "start": 196.01999999999998, "end": 196.94, "probability": 0.901943564414978}, {"word": " why", "start": 196.94, "end": 197.22, "probability": 0.9230788350105286}, {"word": " I", "start": 197.22, "end": 198.8, "probability": 0.9800038933753967}, {"word": " am", "start": 198.8, "end": 198.98, "probability": 0.5624843239784241}, {"word": " through", "start": 198.98, "end": 199.14, "probability": 0.9099339246749878}, {"word": " with", "start": 199.14, "end": 203.72, "probability": 0.7802166938781738}, {"word": " love", "start": 203.72, "end": 204.18, "probability": 0.9962040781974792}]}, {"id": 33, "seek": 21996, "start": 219.96, "end": 222.56, "text": " I am through with love", "tokens": [50365, 286, 669, 807, 365, 959, 51864], "temperature": 0.0, "avg_logprob": -0.2955208718776703, "compression_ratio": 0.7333333333333333, "no_speech_prob": 0.47433769702911377, "words": [{"word": " I", "start": 219.96, "end": 220.44, "probability": 0.017980776727199554}, {"word": " am", "start": 220.44, "end": 220.54, "probability": 0.02706197462975979}, {"word": " through", "start": 220.54, "end": 221.78, "probability": 0.0004996144562028348}, {"word": " with", "start": 221.78, "end": 222.54, "probability": 0.03953330218791962}, {"word": " love", "start": 222.54, "end": 222.56, "probability": 0.007539715152233839}]}], "language": "English"}