{"text": " In my solitude You haunt me With reveries Of days gone by In my solitude You haunt me In my solitude You haunt me With memories That never die I still I still I still I still I sit in my chair. I'm filled with despair. No one could be so sad. With gloom everywhere. I sit and I stare. I know that I'll soon go mad. In my solitude. I'm praying. Dear Lord above. Send back my love. In my solitude. I sit and I stare. I know that I'll soon go mad. In my solitude. I sit and I stare. I know that I'll soon go mad. I sit and I stare. I know that I'll soon go mad. I sit in my chair. I'm filled with despair. No one could be so sad. With gloom everywhere. I sit and I stare. With gloom everywhere. I'll soon go mad. In my solitude. I'm praying. Dear Lord above. Send back my love. Send back my love, send back my love, dear Lord above, send back my love. Send back my love.", "segments": [{"id": 0, "seek": 0, "start": 17.14, "end": 21.0, "text": " In my solitude", "tokens": [50365, 682, 452, 1404, 4377, 51449], "temperature": 0.0, "avg_logprob": -0.7833073139190674, "compression_ratio": 0.6363636363636364, "no_speech_prob": 0.2735978960990906, "words": [{"word": " In", "start": 17.14, "end": 18.54, "probability": 0.5670530200004578}, {"word": " my", "start": 18.54, "end": 19.14, "probability": 0.9759911894798279}, {"word": " solitude", "start": 19.14, "end": 21.0, "probability": 0.9921573102474213}]}, {"id": 1, "seek": 2100, "start": 25.860000000000003, "end": 31.36, "text": " You haunt me", "tokens": [50365, 509, 324, 2760, 385, 50923], "temperature": 0.0, "avg_logprob": -0.3386443456013997, "compression_ratio": 1.0294117647058822, "no_speech_prob": 0.015906009823083878, "words": [{"word": " You", "start": 25.860000000000003, "end": 27.26, "probability": 0.8196401000022888}, {"word": " haunt", "start": 27.26, "end": 28.66, "probability": 0.9620418548583984}, {"word": " me", "start": 28.66, "end": 31.36, "probability": 0.9611270427703857}]}, {"id": 2, "seek": 2100, "start": 33.580000000000005, "end": 36.38, "text": " With reveries", "tokens": [50923, 2022, 18438, 530, 51240], "temperature": 0.0, "avg_logprob": -0.3386443456013997, "compression_ratio": 1.0294117647058822, "no_speech_prob": 0.015906009823083878, "words": [{"word": " With", "start": 33.580000000000005, "end": 34.980000000000004, "probability": 0.8637400269508362}, {"word": " reveries", "start": 34.980000000000004, "end": 36.38, "probability": 0.9929106533527374}]}, {"id": 3, "seek": 2100, "start": 38.5, "end": 42.94, "text": " Of days gone by", "tokens": [51240, 2720, 1708, 2780, 538, 51540], "temperature": 0.0, "avg_logprob": -0.3386443456013997, "compression_ratio": 1.0294117647058822, "no_speech_prob": 0.015906009823083878, "words": [{"word": " Of", "start": 38.059999999999995, "end": 38.76, "probability": 0.8618715405464172}, {"word": " days", "start": 38.76, "end": 40.54, "probability": 0.9982870221138}, {"word": " gone", "start": 40.54, "end": 42.44, "probability": 0.9547582268714905}, {"word": " by", "start": 42.44, "end": 42.94, "probability": 0.9987208247184753}]}, {"id": 4, "seek": 2100, "start": 46.800000000000004, "end": 50.46, "text": " In my solitude", "tokens": [51540, 682, 452, 1404, 4377, 51853], "temperature": 0.0, "avg_logprob": -0.3386443456013997, "compression_ratio": 1.0294117647058822, "no_speech_prob": 0.015906009823083878, "words": [{"word": " In", "start": 46.800000000000004, "end": 48.2, "probability": 0.9585322141647339}, {"word": " my", "start": 48.2, "end": 48.94, "probability": 0.9993284940719604}, {"word": " solitude", "start": 48.94, "end": 50.46, "probability": 0.9987364411354065}]}, {"id": 5, "seek": 2100, "start": 50.46, "end": 50.98, "text": " You haunt me", "tokens": [51853, 509, 324, 2760, 385, 51864], "temperature": 0.0, "avg_logprob": -0.3386443456013997, "compression_ratio": 1.0294117647058822, "no_speech_prob": 0.015906009823083878, "words": [{"word": " You", "start": 50.46, "end": 50.98, "probability": 0.18800318241119385}, {"word": " haunt", "start": 50.98, "end": 50.98, "probability": 0.9026426076889038}, {"word": " me", "start": 50.98, "end": 50.98, "probability": 0.998746395111084}]}, {"id": 6, "seek": 5100, "start": 54.86, "end": 56.34, "text": " In my solitude", "tokens": [50365, 682, 452, 1404, 4377, 50416], "temperature": 1.0, "avg_logprob": -0.6978227996826172, "compression_ratio": 1.6, "no_speech_prob": 0.008561346679925919, "words": [{"word": " In", "start": 54.86, "end": 56.26, "probability": 0.0009992666309699416}, {"word": " my", "start": 56.26, "end": 56.34, "probability": 0.04876359924674034}, {"word": " solitude", "start": 56.34, "end": 56.34, "probability": 0.4937030776964093}]}, {"id": 7, "seek": 5100, "start": 56.34, "end": 61.2, "text": " You haunt me", "tokens": [50416, 509, 324, 2760, 385, 50901], "temperature": 1.0, "avg_logprob": -0.6978227996826172, "compression_ratio": 1.6, "no_speech_prob": 0.008561346679925919, "words": [{"word": " You", "start": 56.34, "end": 56.34, "probability": 0.5477029085159302}, {"word": " haunt", "start": 56.34, "end": 58.48, "probability": 0.4949372150590534}, {"word": " me", "start": 58.48, "end": 61.2, "probability": 0.9533869624137878}]}, {"id": 8, "seek": 5100, "start": 61.72, "end": 65.66, "text": " With memories", "tokens": [50901, 2022, 8495, 51125], "temperature": 1.0, "avg_logprob": -0.6978227996826172, "compression_ratio": 1.6, "no_speech_prob": 0.008561346679925919, "words": [{"word": " With", "start": 61.72, "end": 63.8, "probability": 0.9550986886024475}, {"word": " memories", "start": 63.8, "end": 65.66, "probability": 0.9972658157348633}]}, {"id": 9, "seek": 5100, "start": 68.88, "end": 72.56, "text": " That never die", "tokens": [51125, 663, 1128, 978, 51491], "temperature": 1.0, "avg_logprob": -0.6978227996826172, "compression_ratio": 1.6, "no_speech_prob": 0.008561346679925919, "words": [{"word": " That", "start": 68.88, "end": 70.28, "probability": 0.8902871608734131}, {"word": " never", "start": 70.28, "end": 70.68, "probability": 0.9990034699440002}, {"word": " die", "start": 70.68, "end": 72.56, "probability": 0.9104814529418945}]}, {"id": 10, "seek": 5100, "start": 75.05999999999999, "end": 76.48, "text": " I still", "tokens": [51689, 286, 920, 51853], "temperature": 1.0, "avg_logprob": -0.6978227996826172, "compression_ratio": 1.6, "no_speech_prob": 0.008561346679925919, "words": [{"word": " I", "start": 75.05999999999999, "end": 76.46, "probability": 0.7676168084144592}, {"word": " still", "start": 76.46, "end": 76.48, "probability": 0.15112292766571045}]}, {"id": 11, "seek": 5100, "start": 76.48, "end": 76.6, "text": " I still", "tokens": [51853, 286, 920, 51857], "temperature": 1.0, "avg_logprob": -0.6978227996826172, "compression_ratio": 1.6, "no_speech_prob": 0.008561346679925919, "words": [{"word": " I", "start": 76.48, "end": 76.6, "probability": 0.0019149940926581621}, {"word": " still", "start": 76.6, "end": 76.6, "probability": 0.7411953806877136}]}, {"id": 12, "seek": 5100, "start": 76.6, "end": 76.62, "text": " I still", "tokens": [51857, 286, 920, 51860], "temperature": 1.0, "avg_logprob": -0.6978227996826172, "compression_ratio": 1.6, "no_speech_prob": 0.008561346679925919, "words": [{"word": " I", "start": 76.6, "end": 76.62, "probability": 0.23943105340003967}, {"word": " still", "start": 76.62, "end": 76.62, "probability": 0.9783502817153931}]}, {"id": 13, "seek": 5100, "start": 76.62, "end": 76.62, "text": "", "tokens": [], "temperature": 1.0, "avg_logprob": -0.6978227996826172, "compression_ratio": 1.6, "no_speech_prob": 0.008561346679925919, "words": []}, {"id": 14, "seek": 5100, "start": 76.62, "end": 76.62, "text": "", "tokens": [], "temperature": 1.0, "avg_logprob": -0.6978227996826172, "compression_ratio": 1.6, "no_speech_prob": 0.008561346679925919, "words": []}, {"id": 15, "seek": 5100, "start": 76.62, "end": 76.62, "text": "", "tokens": [], "temperature": 1.0, "avg_logprob": -0.6978227996826172, "compression_ratio": 1.6, "no_speech_prob": 0.008561346679925919, "words": []}, {"id": 16, "seek": 5100, "start": 78.69999999999999, "end": 80.76, "text": " I still", "tokens": [51864, 286, 920, 51865], "temperature": 1.0, "avg_logprob": -0.6978227996826172, "compression_ratio": 1.6, "no_speech_prob": 0.008561346679925919, "words": [{"word": " I", "start": 78.69999999999999, "end": 80.1, "probability": 0.9644607901573181}, {"word": " still", "start": 80.1, "end": 80.76, "probability": 0.9974759221076965}]}, {"id": 17, "seek": 8100, "start": 81.0, "end": 106.42, "text": " I sit in my chair. I'm filled with despair. No one could be so sad. With gloom everywhere. I sit and I stare. I know that I'll soon go mad.", "tokens": [50365, 286, 1394, 294, 452, 6090, 13, 286, 478, 6412, 365, 25763, 13, 883, 472, 727, 312, 370, 4227, 13, 2022, 3114, 298, 5315, 13, 286, 1394, 293, 286, 22432, 13, 286, 458, 300, 286, 603, 2321, 352, 5244, 13, 51726], "temperature": 0.0, "avg_logprob": -0.2284906963969386, "compression_ratio": 1.2410714285714286, "no_speech_prob": 0.7677512168884277, "words": [{"word": " I", "start": 81.0, "end": 81.0, "probability": 0.20310141146183014}, {"word": " sit", "start": 81.0, "end": 81.0, "probability": 0.6525363326072693}, {"word": " in", "start": 81.0, "end": 81.2, "probability": 0.9737499952316284}, {"word": " my", "start": 81.2, "end": 81.44, "probability": 0.9970894455909729}, {"word": " chair.", "start": 81.44, "end": 82.0, "probability": 0.996510922908783}, {"word": " I'm", "start": 82.18, "end": 83.34, "probability": 0.9909501671791077}, {"word": " filled", "start": 83.34, "end": 84.0, "probability": 0.9948185086250305}, {"word": " with", "start": 84.0, "end": 84.62, "probability": 0.9984508752822876}, {"word": " despair.", "start": 84.62, "end": 85.22, "probability": 0.997901439666748}, {"word": " No", "start": 87.5, "end": 88.68, "probability": 0.9921866655349731}, {"word": " one", "start": 88.68, "end": 89.16, "probability": 0.99346524477005}, {"word": " could", "start": 89.16, "end": 89.48, "probability": 0.9955565333366394}, {"word": " be", "start": 89.48, "end": 89.84, "probability": 0.9994320273399353}, {"word": " so", "start": 89.84, "end": 90.74, "probability": 0.9979870319366455}, {"word": " sad.", "start": 90.74, "end": 91.46, "probability": 0.997547447681427}, {"word": " With", "start": 92.72, "end": 93.9, "probability": 0.9919409155845642}, {"word": " gloom", "start": 93.9, "end": 96.1, "probability": 0.9987653195858002}, {"word": " everywhere.", "start": 96.1, "end": 96.86, "probability": 0.9964219331741333}, {"word": " I", "start": 98.64, "end": 99.82, "probability": 0.9982441663742065}, {"word": " sit", "start": 99.82, "end": 100.32, "probability": 0.9980953335762024}, {"word": " and", "start": 100.32, "end": 100.4, "probability": 0.9887050986289978}, {"word": " I", "start": 100.4, "end": 100.62, "probability": 0.9965590834617615}, {"word": " stare.", "start": 100.62, "end": 101.16, "probability": 0.9972647428512573}, {"word": " I", "start": 102.32, "end": 103.5, "probability": 0.9988946318626404}, {"word": " know", "start": 103.5, "end": 103.86, "probability": 0.9996510744094849}, {"word": " that", "start": 103.86, "end": 104.2, "probability": 0.9981938004493713}, {"word": " I'll", "start": 104.2, "end": 104.58, "probability": 0.9810722172260284}, {"word": " soon", "start": 104.58, "end": 104.94, "probability": 0.9980946183204651}, {"word": " go", "start": 104.94, "end": 105.76, "probability": 0.9982339143753052}, {"word": " mad.", "start": 105.76, "end": 106.42, "probability": 0.9994749426841736}]}, {"id": 18, "seek": 10642, "start": 108.38, "end": 118.54, "text": " In my solitude. I'm praying.", "tokens": [50365, 682, 452, 1404, 4377, 13, 286, 478, 15611, 13, 51173], "temperature": 0.0, "avg_logprob": -0.40088197459345276, "compression_ratio": 0.9696969696969697, "no_speech_prob": 0.00999215804040432, "words": [{"word": " In", "start": 108.38, "end": 109.78, "probability": 0.3860171437263489}, {"word": " my", "start": 109.78, "end": 110.42, "probability": 0.9879317879676819}, {"word": " solitude.", "start": 110.42, "end": 111.32, "probability": 0.9920810461044312}, {"word": " I'm", "start": 116.16, "end": 117.56, "probability": 0.9749662578105927}, {"word": " praying.", "start": 117.56, "end": 118.54, "probability": 0.9959604144096375}]}, {"id": 19, "seek": 10642, "start": 124.18, "end": 133.92, "text": " Dear Lord above. Send back my love.", "tokens": [51173, 14383, 3257, 3673, 13, 17908, 646, 452, 959, 13, 51806], "temperature": 0.0, "avg_logprob": -0.40088197459345276, "compression_ratio": 0.9696969696969697, "no_speech_prob": 0.00999215804040432, "words": [{"word": " Dear", "start": 124.18, "end": 125.58, "probability": 0.9434745907783508}, {"word": " Lord", "start": 125.58, "end": 126.74, "probability": 0.9527881741523743}, {"word": " above.", "start": 126.74, "end": 127.2, "probability": 0.9957330822944641}, {"word": " Send", "start": 130.04, "end": 131.44, "probability": 0.995140790939331}, {"word": " back", "start": 131.44, "end": 132.4, "probability": 0.9968858361244202}, {"word": " my", "start": 132.4, "end": 133.14, "probability": 0.9964154958724976}, {"word": " love.", "start": 133.14, "end": 133.92, "probability": 0.9944803714752197}]}, {"id": 20, "seek": 13642, "start": 136.46, "end": 147.74, "text": " In my solitude. I sit and I stare. I know that I'll soon go mad.", "tokens": [50365, 682, 452, 1404, 4377, 13, 286, 1394, 293, 286, 22432, 13, 286, 458, 300, 286, 603, 2321, 352, 5244, 13, 51864], "temperature": 0.0, "avg_logprob": -0.3197715335422092, "compression_ratio": 1.8695652173913044, "no_speech_prob": 0.08674496412277222, "words": [{"word": " In", "start": 136.46, "end": 137.3, "probability": 0.0008498458191752434}, {"word": " my", "start": 137.3, "end": 137.3, "probability": 0.017460161820054054}, {"word": " solitude.", "start": 137.3, "end": 137.34, "probability": 0.365140974559381}, {"word": " I", "start": 144.02, "end": 144.86, "probability": 0.03196624666452408}, {"word": " sit", "start": 144.86, "end": 144.86, "probability": 0.0019764606840908527}, {"word": " and", "start": 144.86, "end": 145.3, "probability": 0.1352217197418213}, {"word": " I", "start": 145.3, "end": 145.3, "probability": 0.10247684270143509}, {"word": " stare.", "start": 145.3, "end": 145.3, "probability": 0.0036313694436103106}, {"word": " I", "start": 145.3, "end": 145.66, "probability": 0.2693255543708801}, {"word": " know", "start": 145.66, "end": 145.86, "probability": 0.008160276338458061}, {"word": " that", "start": 145.86, "end": 147.4, "probability": 0.1737271100282669}, {"word": " I'll", "start": 147.4, "end": 147.54, "probability": 0.15273271687328815}, {"word": " soon", "start": 147.54, "end": 147.62, "probability": 0.0038472176529467106}, {"word": " go", "start": 147.62, "end": 147.74, "probability": 0.008540746755897999}, {"word": " mad.", "start": 147.74, "end": 147.74, "probability": 0.00212844624184072}]}, {"id": 21, "seek": 13642, "start": 147.74, "end": 159.02, "text": " In my solitude. I sit and I stare. I know that I'll soon go mad.", "tokens": [51864, 682, 452, 1404, 4377, 13, 286, 1394, 293, 286, 22432, 13, 286, 458, 300, 286, 603, 2321, 352, 5244, 13, 51865], "temperature": 0.0, "avg_logprob": -0.3197715335422092, "compression_ratio": 1.8695652173913044, "no_speech_prob": 0.08674496412277222, "words": [{"word": " In", "start": 147.74, "end": 148.16, "probability": 0.042888954281806946}, {"word": " my", "start": 148.16, "end": 148.34, "probability": 0.7746911644935608}, {"word": " solitude.", "start": 148.34, "end": 150.84, "probability": 0.9824833571910858}, {"word": " I", "start": 150.84, "end": 150.84, "probability": 0.8997301459312439}, {"word": " sit", "start": 150.84, "end": 151.04, "probability": 0.8015671372413635}, {"word": " and", "start": 151.04, "end": 151.92, "probability": 0.9595317840576172}, {"word": " I", "start": 151.92, "end": 152.44, "probability": 0.9914124011993408}, {"word": " stare.", "start": 152.44, "end": 152.94, "probability": 0.967648446559906}, {"word": " I", "start": 154.72, "end": 155.56, "probability": 0.89327073097229}, {"word": " know", "start": 155.56, "end": 156.18, "probability": 0.8415922522544861}, {"word": " that", "start": 156.18, "end": 156.46, "probability": 0.9912512898445129}, {"word": " I'll", "start": 156.46, "end": 156.6, "probability": 0.9692934155464172}, {"word": " soon", "start": 156.6, "end": 156.92, "probability": 0.9940654039382935}, {"word": " go", "start": 156.92, "end": 158.9, "probability": 0.9982184767723083}, {"word": " mad.", "start": 158.9, "end": 159.02, "probability": 0.9942979216575623}]}, {"id": 22, "seek": 16642, "start": 176.06, "end": 196.02, "text": " I sit and I stare. I know that I'll soon go mad.", "tokens": [50365, 286, 1394, 293, 286, 22432, 13, 286, 458, 300, 286, 603, 2321, 352, 5244, 13, 51864], "temperature": 0.0, "avg_logprob": -0.265814913643731, "compression_ratio": 0.8888888888888888, "no_speech_prob": 0.13171187043190002, "words": [{"word": " I", "start": 176.06, "end": 177.34, "probability": 0.0233323872089386}, {"word": " sit", "start": 177.34, "end": 178.12, "probability": 3.30428738379851e-05}, {"word": " and", "start": 178.12, "end": 178.44, "probability": 0.07586750388145447}, {"word": " I", "start": 178.44, "end": 178.58, "probability": 0.06536390632390976}, {"word": " stare.", "start": 178.58, "end": 178.94, "probability": 0.0019213324412703514}, {"word": " I", "start": 180.98, "end": 182.26, "probability": 0.44752275943756104}, {"word": " know", "start": 182.26, "end": 183.72, "probability": 0.0030278845224529505}, {"word": " that", "start": 183.72, "end": 189.38, "probability": 0.13911953568458557}, {"word": " I'll", "start": 189.38, "end": 189.88, "probability": 0.13559509348124266}, {"word": " soon", "start": 189.88, "end": 191.52, "probability": 0.0032079992815852165}, {"word": " go", "start": 191.52, "end": 195.96, "probability": 0.010012245737016201}, {"word": " mad.", "start": 195.96, "end": 196.02, "probability": 0.00478729885071516}]}, {"id": 23, "seek": 19642, "start": 201.6, "end": 215.74, "text": " I sit in my chair. I'm filled with despair. No one could be so sad.", "tokens": [50365, 286, 1394, 294, 452, 6090, 13, 286, 478, 6412, 365, 25763, 13, 883, 472, 727, 312, 370, 4227, 13, 51365], "temperature": 0.0, "avg_logprob": -0.1986187253679548, "compression_ratio": 1.1595744680851063, "no_speech_prob": 0.008858171291649342, "words": [{"word": " I", "start": 201.6, "end": 203.0, "probability": 0.6251468062400818}, {"word": " sit", "start": 203.0, "end": 203.62, "probability": 0.9723419547080994}, {"word": " in", "start": 203.62, "end": 205.12, "probability": 0.9838725924491882}, {"word": " my", "start": 205.12, "end": 205.5, "probability": 0.9985028505325317}, {"word": " chair.", "start": 205.5, "end": 206.02, "probability": 0.996468186378479}, {"word": " I'm", "start": 206.62, "end": 208.02, "probability": 0.014319367008283734}, {"word": " filled", "start": 208.02, "end": 208.02, "probability": 0.7558218240737915}, {"word": " with", "start": 208.02, "end": 208.96, "probability": 0.9963906407356262}, {"word": " despair.", "start": 208.96, "end": 209.7, "probability": 0.9973325729370117}, {"word": " No", "start": 211.36, "end": 212.76, "probability": 0.9580584168434143}, {"word": " one", "start": 212.76, "end": 213.14, "probability": 0.9975547194480896}, {"word": " could", "start": 213.14, "end": 213.38, "probability": 0.9974574446678162}, {"word": " be", "start": 213.38, "end": 213.7, "probability": 0.9996702671051025}, {"word": " so", "start": 213.7, "end": 214.42, "probability": 0.9977580904960632}, {"word": " sad.", "start": 214.42, "end": 215.74, "probability": 0.9992272853851318}]}, {"id": 24, "seek": 19642, "start": 216.84, "end": 225.12, "text": " With gloom everywhere. I sit and I stare.", "tokens": [51365, 2022, 3114, 298, 5315, 13, 286, 1394, 293, 286, 22432, 13, 51815], "temperature": 0.0, "avg_logprob": -0.1986187253679548, "compression_ratio": 1.1595744680851063, "no_speech_prob": 0.008858171291649342, "words": [{"word": " With", "start": 216.84, "end": 218.24, "probability": 0.9919260144233704}, {"word": " gloom", "start": 218.24, "end": 219.9, "probability": 0.9971368312835693}, {"word": " everywhere.", "start": 219.9, "end": 221.0, "probability": 0.9971677660942078}, {"word": " I", "start": 221.9, "end": 222.64, "probability": 0.9490118622779846}, {"word": " sit", "start": 222.64, "end": 223.2, "probability": 0.9995172023773193}, {"word": " and", "start": 223.2, "end": 223.36, "probability": 0.9979015588760376}, {"word": " I", "start": 223.36, "end": 223.86, "probability": 0.9998258948326111}, {"word": " stare.", "start": 223.86, "end": 225.12, "probability": 0.9967265129089355}]}, {"id": 25, "seek": 22642, "start": 226.42, "end": 231.52, "text": " With gloom everywhere. I'll soon go mad.", "tokens": [50365, 2022, 3114, 298, 5315, 13, 286, 603, 2321, 352, 5244, 13, 50664], "temperature": 0.8, "avg_logprob": -0.3766169018215603, "compression_ratio": 1.105263157894737, "no_speech_prob": 0.006183423101902008, "words": [{"word": " With", "start": 226.42, "end": 226.56, "probability": 0.00010236170783173293}, {"word": " gloom", "start": 226.56, "end": 226.56, "probability": 0.1562190881541028}, {"word": " everywhere.", "start": 226.56, "end": 226.56, "probability": 0.0006792687345296144}, {"word": " I'll", "start": 228.74, "end": 230.14, "probability": 0.9279561638832092}, {"word": " soon", "start": 230.14, "end": 230.5, "probability": 0.9974863529205322}, {"word": " go", "start": 230.5, "end": 230.88, "probability": 0.9905380010604858}, {"word": " mad.", "start": 230.88, "end": 231.52, "probability": 0.9922851324081421}]}, {"id": 26, "seek": 22642, "start": 232.39999999999998, "end": 242.44, "text": " In my solitude. I'm praying.", "tokens": [50664, 682, 452, 1404, 4377, 13, 286, 478, 15611, 13, 51414], "temperature": 0.8, "avg_logprob": -0.3766169018215603, "compression_ratio": 1.105263157894737, "no_speech_prob": 0.006183423101902008, "words": [{"word": " In", "start": 232.12, "end": 232.82, "probability": 0.9138374924659729}, {"word": " my", "start": 232.82, "end": 233.78, "probability": 0.994682252407074}, {"word": " solitude.", "start": 233.78, "end": 235.1, "probability": 0.9861300587654114}, {"word": " I'm", "start": 240.18, "end": 241.58, "probability": 0.9392460882663727}, {"word": " praying.", "start": 241.58, "end": 242.44, "probability": 0.978569746017456}]}, {"id": 27, "seek": 22642, "start": 247.84, "end": 256.4, "text": " Dear Lord above. Send back my love.", "tokens": [51414, 14383, 3257, 3673, 13, 17908, 646, 452, 959, 13, 51864], "temperature": 0.8, "avg_logprob": -0.3766169018215603, "compression_ratio": 1.105263157894737, "no_speech_prob": 0.006183423101902008, "words": [{"word": " Dear", "start": 247.84, "end": 249.24, "probability": 0.8661137819290161}, {"word": " Lord", "start": 249.24, "end": 250.54, "probability": 0.8155229091644287}, {"word": " above.", "start": 250.54, "end": 252.28, "probability": 0.45811575651168823}, {"word": " Send", "start": 253.64, "end": 255.04, "probability": 0.9173542857170105}, {"word": " back", "start": 255.04, "end": 255.88, "probability": 0.8883665204048157}, {"word": " my", "start": 255.88, "end": 256.4, "probability": 0.043788596987724304}, {"word": " love.", "start": 256.4, "end": 256.4, "probability": 0.02846946381032467}]}, {"id": 28, "seek": 25642, "start": 256.42, "end": 280.14, "text": " Send back my love, send back my love, dear Lord above, send back my love.", "tokens": [50365, 17908, 646, 452, 959, 11, 2845, 646, 452, 959, 11, 6875, 3257, 3673, 11, 2845, 646, 452, 959, 13, 51615], "temperature": 0.0, "avg_logprob": -0.5286244912581011, "compression_ratio": 1.6222222222222222, "no_speech_prob": 0.6179701685905457, "words": [{"word": " Send", "start": 256.42, "end": 257.36, "probability": 0.2056417465209961}, {"word": " back", "start": 257.36, "end": 257.36, "probability": 0.9293643236160278}, {"word": " my", "start": 257.36, "end": 257.36, "probability": 0.9528053402900696}, {"word": " love,", "start": 257.36, "end": 258.1, "probability": 0.979755163192749}, {"word": " send", "start": 258.86, "end": 259.82, "probability": 0.26165494322776794}, {"word": " back", "start": 259.82, "end": 260.52, "probability": 0.996767520904541}, {"word": " my", "start": 260.52, "end": 261.22, "probability": 0.995259702205658}, {"word": " love,", "start": 261.22, "end": 262.02, "probability": 0.9973015785217285}, {"word": " dear", "start": 262.44, "end": 263.82, "probability": 0.5975543856620789}, {"word": " Lord", "start": 263.82, "end": 266.02, "probability": 0.8574520945549011}, {"word": " above,", "start": 266.02, "end": 269.04, "probability": 0.9103094339370728}, {"word": " send", "start": 269.42, "end": 272.94, "probability": 0.8879948854446411}, {"word": " back", "start": 272.94, "end": 274.1, "probability": 0.99724280834198}, {"word": " my", "start": 274.1, "end": 278.32, "probability": 0.9717268347740173}, {"word": " love.", "start": 278.32, "end": 280.14, "probability": 0.9975729584693909}]}, {"id": 29, "seek": 28642, "start": 286.42, "end": 286.6, "text": " Send back my love.", "tokens": [50365, 17908, 646, 452, 959, 13, 51864], "temperature": 0.0, "avg_logprob": -0.5868340730667114, "compression_ratio": 0.6923076923076923, "no_speech_prob": 0.1865418404340744, "words": [{"word": " Send", "start": 286.42, "end": 286.6, "probability": 4.259057459421456e-05}, {"word": " back", "start": 286.6, "end": 286.6, "probability": 0.0016314765671268106}, {"word": " my", "start": 286.6, "end": 286.6, "probability": 0.07166224718093872}, {"word": " love.", "start": 286.6, "end": 286.6, "probability": 0.32888996601104736}]}], "language": "English"}